smm_wrapper/__init__.py
smm_wrapper/api.py
smm_wrapper/smm.py
smm_wrapper/views.py
smm_wrapper-1.3.1.dist-info/LICENSE
smm_wrapper-1.3.1.dist-info/METADATA
smm_wrapper-1.3.1.dist-info/WHEEL
smm_wrapper-1.3.1.dist-info/top_level.txt
smm_wrapper-1.3.1.dist-info/RECORD
